dsnet/__init__.py
dsnet/base.py
dsnet/msg.py
dsnet-0.0.0.dist-info/DESCRIPTION.rst
dsnet-0.0.0.dist-info/METADATA
dsnet-0.0.0.dist-info/RECORD
dsnet-0.0.0.dist-info/WHEEL
dsnet-0.0.0.dist-info/metadata.json
dsnet-0.0.0.dist-info/top_level.txt
